neuro_int_mamba/__init__.py
neuro_int_mamba/model.py
neuro_int_mamba/nn.py
neuro_int_mamba-0.1.0.dist-info/METADATA
neuro_int_mamba-0.1.0.dist-info/WHEEL
neuro_int_mamba-0.1.0.dist-info/RECORD
