Metadata-Version: 2.4
Name: neuro-int-mamba
Version: 0.1.0
Summary: A Bio-inspired Mamba Architecture for Dexterous Manipulation with Intrinsic Neural Timescales
Project-URL: Homepage, https://github.com/yourusername/neuro-int-mamba
Project-URL: Repository, https://github.com/yourusername/neuro-int-mamba
Author-email: Your Name <your.email@example.com>
License: MIT
Requires-Python: >=3.13
Requires-Dist: torch>=2.9.1
